falconratelimit/__init__.py
falconratelimit/ratelimit.py
falcon_ratelimit-1.2.dist-info/LICENSE
falcon_ratelimit-1.2.dist-info/METADATA
falcon_ratelimit-1.2.dist-info/WHEEL
falcon_ratelimit-1.2.dist-info/top_level.txt
falcon_ratelimit-1.2.dist-info/RECORD
