Metadata-Version: 2.1
Name: falcon-ratelimit
Version: 1.2
Summary: A rate limiter plugin for Falcon
Home-page: https://github.com/piotrmaslanka/falcon-ratelimit
Author: Piotr Maślanka
Author-email: piotr.maslanka@henrietta.com.pl
License: UNKNOWN
Platform: UNKNOWN
Classifier: Programming Language :: Python
Classifier: Programming Language :: Python :: 2.7
Classifier: Programming Language :: Python :: 3.4
Classifier: Programming Language :: Python :: 3.5
Classifier: Programming Language :: Python :: Implementation :: CPython
Classifier: Programming Language :: Python :: Implementation :: PyPy
Classifier: Operating System :: OS Independent
Classifier: Development Status :: 4 - Beta
Classifier: License :: OSI Approved :: MIT License
Classifier: Topic :: Software Development :: Libraries
Classifier: Topic :: Internet :: WWW/HTTP :: Session
Requires-Dist: falcon
Requires-Dist: six
